pyrfc6266.py
pyrfc6266-1.0.2.dist-info/LICENSE
pyrfc6266-1.0.2.dist-info/METADATA
pyrfc6266-1.0.2.dist-info/WHEEL
pyrfc6266-1.0.2.dist-info/top_level.txt
pyrfc6266-1.0.2.dist-info/RECORD
