Metadata-Version: 2.1
Name: pyrfc6266
Version: 1.0.2
Summary: RFC6266 implementation in Python
Home-page: https://github.com/JohnDoee/pyrfc6266
Author: Anders Jensen
Author-email: andersandjensen@gmail.com
License: MIT
Platform: UNKNOWN
Classifier: Development Status :: 4 - Beta
Classifier: License :: OSI Approved :: MIT License
License-File: LICENSE
Requires-Dist: pyparsing (~=3.0.7)
